ret/__init__.py
ret/__main__.py
ret/cmd_opts.py
ret-0.1.4.dist-info/entry_points.txt
ret-0.1.4.dist-info/LICENSE
ret-0.1.4.dist-info/WHEEL
ret-0.1.4.dist-info/METADATA
ret-0.1.4.dist-info/RECORD
