Metadata-Version: 2.1
Name: ret
Version: 0.1.4
Summary: A pure-python command-line regular expression tool for stream filtering, extracting, and parsing.
Home-page: https://github.com/ThatXliner/ret/
License: GPL-3.0-or-later
Keywords: regex,cli,tool,grep
Author: Bryan Hu
Author-email: bryan.hu.2020@gmail.com
Requires-Python: >=3.6,<4.0
Classifier: Development Status :: 4 - Beta
Classifier: Environment :: Console
Classifier: Intended Audience :: Developers
Classifier: License :: OSI Approved :: GNU General Public License v3 or later (GPLv3+)
Classifier: Natural Language :: English
Classifier: Operating System :: OS Independent
Classifier: Programming Language :: Python :: 3
Classifier: Programming Language :: Python :: 3.10
Classifier: Programming Language :: Python :: 3.6
Classifier: Programming Language :: Python :: 3.7
Classifier: Programming Language :: Python :: 3.8
Classifier: Programming Language :: Python :: 3.9
Classifier: Programming Language :: Python :: Implementation :: CPython
Classifier: Programming Language :: Python :: Implementation :: PyPy
Classifier: Topic :: Utilities
Classifier: Typing :: Typed
Provides-Extra: regex
Project-URL: Bug Tracker, https://github.com/ThatXliner/ret/issues
Project-URL: Source Code, https://github.com/ThatXliner/ret
Project-URL: Say Thanks! , https://saythanks.io/to/bryan.hu.2020@gmail.com
